auth0_easy_api/__init__.py
auth0_easy_api/auth0_easy_api.py
auth0_easy_api/auth0_easy_api_core.py
examples/__init__.py
examples/desktop_gui_client_example.py
examples/server_api_example.py
auth0_easy_api-1.0.5.dist-info/LICENSE
auth0_easy_api-1.0.5.dist-info/METADATA
auth0_easy_api-1.0.5.dist-info/WHEEL
auth0_easy_api-1.0.5.dist-info/top_level.txt
auth0_easy_api-1.0.5.dist-info/RECORD
